channel2pdf/__init__.py
channel2pdf/article.py
channel2pdf/find_links.py
channel2pdf/find_resource.py
channel2pdf/gen_index.py
channel2pdf/index.py
channel2pdf-0.0.28.dist-info/LICENSE
channel2pdf-0.0.28.dist-info/METADATA
channel2pdf-0.0.28.dist-info/WHEEL
channel2pdf-0.0.28.dist-info/top_level.txt
channel2pdf-0.0.28.dist-info/RECORD
