Metadata-Version: 2.1
Name: channel2pdf
Version: 0.0.28
Summary: Export Telegram Channel to PDF
Home-page: https://github.com/gaoyunzhi/channel2pdf
Author: Yunzhi Gao
Author-email: gaoyunzhi@gmail.com
License: UNKNOWN
Platform: UNKNOWN
Classifier: Programming Language :: Python :: 3
Classifier: License :: OSI Approved :: MIT License
Classifier: Operating System :: OS Independent
Requires-Python: >=3.0
License-File: LICENSE
Requires-Dist: bs4
Requires-Dist: telegram-util
Requires-Dist: cached-url
Requires-Dist: pyyaml
Requires-Dist: readee
Requires-Dist: telethon
